MANIFEST.in
README.rst
conf.yaml.example
setup.py
dns_firewall/__init__.py
dns_firewall/main.py
dns_firewall/ui.py
dns_firewall.egg-info/PKG-INFO
dns_firewall.egg-info/SOURCES.txt
dns_firewall.egg-info/dependency_links.txt
dns_firewall.egg-info/entry_points.txt
dns_firewall.egg-info/not-zip-safe
dns_firewall.egg-info/requires.txt
dns_firewall.egg-info/top_level.txt
dns_firewall/data/bkg.png
dns_firewall/data/green.png
dns_firewall/data/orange.png
dns_firewall/data/red.png