Metadata-Version: 1.1
Name: dns-firewall
Version: 0.0.4
Summary: Local DNS Firewall
Home-page: https://github.com/FedericoCeratto/dns-firewall
Author: Federico Ceratto
Author-email: federico.ceratto@gmail.com
License: AGPLv3+
Keywords: desktop security
Platform: Linux
Classifier: Environment :: Console
Classifier: Environment :: X11 Applications :: GTK
Classifier: License :: OSI Approved :: GNU Affero General Public License v3 or later (AGPLv3+)
Classifier: Natural Language :: English
Classifier: Operating System :: POSIX :: Linux
Classifier: Programming Language :: Python
Classifier: Programming Language :: Python :: 2.7
Classifier: Topic :: Security
